{
  "smileys": [
    "😀", "😃", "😄", "😁", "😆", "😅", "🤣", "😂", "🙂", "🙃",
    "😉", "😊", "😇", "🥰", "😍", "🤩", "😘", "😗", "😚", "😙",
    "🥲", "😋", "😛", "😜", "🤪", "😝", "🤑", "🤗", "🤭", "🫢",
    "🤫", "🤔", "🫡", "🤐", "🤨", "😐", "😑", "😶", "🫥", "😏",
    "😒", "🙄", "😬", "🤥", "😌", "😔", "😪", "🤤", "😴", "🥹"
  ],
  "gestures": [
    "👍", "👎", "👊", "✊", "🤛", "🤜", "👏", "🙌", "🫶", "👐",
    "🤲", "🤝", "🙏", "✌️", "🤞", "🫰", "🤟", "🤘", "🤙", "👈",
    "👉", "👆", "👇", "☝️", "✋", "🤚", "🖐️", "🖖", "👋", "🤏",
    "💪", "🦾", "🖕", "✍️", "🫵", "🫲", "🫳", "🫴", "🫱", "👌",
    "🤌", "🤏", "👀", "👁️", "👅", "👄", "🫦", "💅", "🤳", "💃"
  ],
  "hearts": [
    "❤️", "🧡", "💛", "💚", "💙", "💜", "🖤", "🤍", "🤎", "💔",
    "❤️‍🔥", "❤️‍🩹", "❣️", "💕", "💞", "💓", "💗", "💖", "💘", "💝",
    "💟", "♥️", "🫀", "💑", "👩‍❤️‍👨", "👩‍❤️‍👩", "👨‍❤️‍👨", "💏", "👩‍❤️‍💋‍👨", "😍",
    "🥰", "😘", "💋", "😻", "🩷", "🩵", "🩶", "🫶", "💌", "🏩"
  ],
  "animals": [
    "🐶", "🐱", "🐭", "🐹", "🐰", "🦊", "🐻", "🐼", "🐻‍❄️", "🐨",
    "🐯", "🦁", "🐮", "🐷", "🐸", "🐵", "🙈", "🙉", "🙊", "🐒",
    "🐔", "🐧", "🐦", "🐤", "🦆", "🦅", "🦉", "🦇", "🐺", "🐗",
    "🐴", "🦄", "🐝", "🐛", "🦋", "🐌", "🐞", "🐜", "🪲", "🐢",
    "🐍", "🦎", "🦂", "🐙", "🦑", "🦐", "🐠", "🐟", "🐬", "🐳"
  ],
  "food": [
    "🍕", "🍔", "🍟", "🌭", "🍿", "🧂", "🥓", "🥚", "🍳", "🧇",
    "🥞", "🧈", "🍞", "🥐", "🥖", "🫓", "🥨", "🧀", "🥗", "🥙",
    "🌮", "🌯", "🫔", "🥘", "🍝", "🍜", "🍲", "🍛", "🍣", "🍱",
    "🥟", "🦪", "🍤", "🍙", "🍚", "🍘", "🍥", "🥠", "🍰", "🎂",
    "🧁", "🍩", "🍪", "🍫", "🍬", "🍭", "☕", "🍵", "🧃", "🍺"
  ],
  "nature": [
    "🌸", "💮", "🏵️", "🌹", "🥀", "🌺", "🌻", "🌼", "🌷", "🪷",
    "🌱", "🪴", "🌲", "🌳", "🌴", "🌵", "🌾", "🌿", "☘️", "🍀",
    "🍁", "🍂", "🍃", "🍄", "🌰", "🌍", "🌎", "🌏", "🌕", "🌙",
    "⭐", "🌟", "✨", "💫", "☀️", "🌤️", "⛅", "🌈", "☁️", "🌧️",
    "⛈️", "🌩️", "❄️", "💧", "💦", "🌊", "🔥", "🌪️", "🫧", "🪸"
  ],
  "objects": [
    "💻", "🖥️", "📱", "📲", "⌨️", "🖨️", "🖱️", "💾", "💿", "📀",
    "📷", "📸", "📹", "🎥", "📽️", "🎞️", "📞", "☎️", "📟", "📠",
    "📺", "📻", "🎙️", "🎚️", "🎛️", "⏰", "⌚", "📡", "🔋", "🔌",
    "💡", "🔦", "🕯️", "🎧", "🎮", "🕹️", "🏆", "🎖️", "🏅", "🥇",
    "🎯", "🎲", "🧩", "🎭", "🎨", "🖌️", "📝", "✏️", "📚", "🔑"
  ],
  "flags": [
    "🇧🇷", "🇺🇸", "🇦🇷", "🇵🇹", "🇯🇵", "🇰🇷", "🇨🇳", "🇮🇳", "🇩🇪", "🇫🇷",
    "🇬🇧", "🇮🇹", "🇪🇸", "🇲🇽", "🇨🇦", "🇦🇺", "🇷🇺", "🇨🇴", "🇨🇱", "🇵🇪",
    "🇺🇾", "🇵🇾", "🇧🇴", "🇪🇨", "🇻🇪", "🇨🇺", "🇵🇦", "🇨🇷", "🇸🇪", "🇳🇴",
    "🇫🇮", "🇩🇰", "🇳🇱", "🇧🇪", "🇨🇭", "🇦🇹", "🇮🇪", "🇵🇱", "🇹🇷", "🇿🇦",
    "🇪🇬", "🇳🇬", "🇰🇪", "🇲🇦", "🇮🇱", "🇦🇪", "🇸🇦", "🇹🇭", "🇻🇳", "🇵🇭"
  ],
  "activities": [
    "⚽", "🏀", "🏈", "⚾", "🥎", "🎾", "🏐", "🏉", "🥏", "🎱",
    "🏓", "🏸", "🏒", "🥊", "🥋", "🥅", "⛳", "⛸️", "🎣", "🤿",
    "🎿", "🛷", "🥌", "🎯", "🪀", "🪁", "🎲", "🧩", "🎭", "🎨",
    "🎬", "🎤", "🎧", "🎼", "🎹", "🥁", "🪘", "🎷", "🎺", "🎸",
    "🪕", "🎻", "🎪", "🤹", "🎰", "🛹", "🛼", "🏄", "🏊", "🚴"
  ],
  "travel": [
    "✈️", "🛫", "🛬", "🛩️", "🚀", "🛸", "🚁", "🚗", "🚕", "🚙",
    "🚌", "🚎", "🏎️", "🚓", "🚑", "🚒", "🚐", "🛻", "🚚", "🚛",
    "🚂", "🚃", "🚄", "🚅", "🚆", "🚇", "🛳️", "⛴️", "🚢", "⛵",
    "🏖️", "🏝️", "🏜️", "🏔️", "⛰️", "🗻", "🌋", "🏕️", "🗺️", "🧳",
    "🗼", "🗽", "🏰", "🕌", "🕍", "⛩️", "🛕", "🎡", "🎢", "🌍"
  ]
}
